dataclass_codec/__init__.py
dataclass_codec/decode.py
dataclass_codec/encode.py
dataclass_codec/py.typed
dataclass_codec/tests/test_dataclass_codec.py
dataclass_codec/tests/test_python3_10.py
dataclass_codec/tests/test_python3_9.py
dataclass_codec/types_predicates.py
dataclass_codec-0.5.10.dist-info/METADATA
dataclass_codec-0.5.10.dist-info/WHEEL
dataclass_codec-0.5.10.dist-info/RECORD
