Metadata-Version: 2.1
Name: dataclass-codec
Version: 0.5.10
Summary: 
Author: lucas.silva
Author-email: me@luscasleo.dev
Requires-Python: >=3.8,<4.0
Classifier: Programming Language :: Python :: 3
Classifier: Programming Language :: Python :: 3.8
Classifier: Programming Language :: Python :: 3.9
Classifier: Programming Language :: Python :: 3.10
Classifier: Programming Language :: Python :: 3.11
Requires-Dist: isort (>=5.13.2,<6.0.0)
